claude_knowledge_catalyst/__init__.py
claude_knowledge_catalyst/__main__.py
claude_knowledge_catalyst/ai/__init__.py
claude_knowledge_catalyst/ai/ai_assistant.py
claude_knowledge_catalyst/ai/classification_engine.py
claude_knowledge_catalyst/ai/pattern_loader.py
claude_knowledge_catalyst/ai/smart_classifier.py
claude_knowledge_catalyst/ai/smart_classifier_refactored.py
claude_knowledge_catalyst/ai/yake_extractor.py
claude_knowledge_catalyst/ai/patterns/content_patterns.yaml
claude_knowledge_catalyst/ai/patterns/domain_patterns.yaml
claude_knowledge_catalyst/ai/patterns/tech_patterns.yaml
claude_knowledge_catalyst/analytics/__init__.py
claude_knowledge_catalyst/analytics/knowledge_analytics.py
claude_knowledge_catalyst/analytics/usage_statistics.py
claude_knowledge_catalyst/automation/metadata_enhancer.py
claude_knowledge_catalyst/automation/structure_automation.py
claude_knowledge_catalyst/cli/__init__.py
claude_knowledge_catalyst/cli/interactive.py
claude_knowledge_catalyst/cli/main.py
claude_knowledge_catalyst/cli/migrate_commands.py
claude_knowledge_catalyst/cli/smart_sync.py
claude_knowledge_catalyst/cli/structure_commands.py
claude_knowledge_catalyst/core/__init__.py
claude_knowledge_catalyst/core/claude_md_processor.py
claude_knowledge_catalyst/core/config.py
claude_knowledge_catalyst/core/config_migration.py
claude_knowledge_catalyst/core/hybrid_config.py
claude_knowledge_catalyst/core/metadata.py
claude_knowledge_catalyst/core/structure_validator.py
claude_knowledge_catalyst/core/tag_standards.py
claude_knowledge_catalyst/core/watcher.py
claude_knowledge_catalyst/obsidian/query_builder.py
claude_knowledge_catalyst/sync/__init__.py
claude_knowledge_catalyst/sync/compatibility.py
claude_knowledge_catalyst/sync/hybrid_manager.py
claude_knowledge_catalyst/sync/obsidian.py
claude_knowledge_catalyst/templates/__init__.py
claude_knowledge_catalyst/templates/hybrid_templates.py
claude_knowledge_catalyst/templates/manager.py
claude_knowledge_catalyst-0.10.1.dist-info/METADATA
claude_knowledge_catalyst-0.10.1.dist-info/WHEEL
claude_knowledge_catalyst-0.10.1.dist-info/entry_points.txt
claude_knowledge_catalyst-0.10.1.dist-info/licenses/LICENSE
claude_knowledge_catalyst-0.10.1.dist-info/RECORD
