Metadata-Version: 2.4
Name: claude-knowledge-catalyst
Version: 0.10.1
Summary: AI-powered knowledge management with YAKE keyword extraction for Claude Code development
Project-URL: Homepage, https://github.com/drillan/claude-knowledge-catalyst
Project-URL: Documentation, https://claude-knowledge-catalyst.readthedocs.io/
Project-URL: Repository, https://github.com/drillan/claude-knowledge-catalyst.git
Project-URL: Issues, https://github.com/drillan/claude-knowledge-catalyst/issues
Project-URL: Read the Docs, https://claude-knowledge-catalyst.readthedocs.io/
Project-URL: Source Code, https://github.com/drillan/claude-knowledge-catalyst
Author: CKC Contributors
License-Expression: MIT
License-File: LICENSE
Keywords: ai,claude,development,keyword-extraction,knowledge,management,nlp,obsidian,yake
Classifier: Development Status :: 4 - Beta
Classifier: Intended Audience :: Developers
Classifier: License :: OSI Approved :: MIT License
Classifier: Operating System :: OS Independent
Classifier: Programming Language :: Python :: 3
Classifier: Programming Language :: Python :: 3.11
Classifier: Programming Language :: Python :: 3.12
Classifier: Topic :: Software Development :: Documentation
Classifier: Topic :: Software Development :: Libraries :: Python Modules
Classifier: Topic :: Text Processing :: Markup :: Markdown
Requires-Python: >=3.11
Requires-Dist: gitpython>=3.1.0
Requires-Dist: jinja2>=3.1.0
Requires-Dist: langdetect>=1.0.9
Requires-Dist: matplotlib>=3.10.3
Requires-Dist: psutil>=7.0.0
Requires-Dist: pydantic>=2.0.0
Requires-Dist: python-frontmatter>=1.0.0
Requires-Dist: pyyaml>=6.0
Requires-Dist: rich>=13.0.0
Requires-Dist: seaborn>=0.13.2
Requires-Dist: typer>=0.9.0
Requires-Dist: unidecode>=1.3.0
Requires-Dist: watchdog>=3.0.0
Requires-Dist: yake>=0.4.8
Provides-Extra: dev
Requires-Dist: mypy>=1.0.0; extra == 'dev'
Requires-Dist: pre-commit>=3.0.0; extra == 'dev'
Requires-Dist: pytest-cov>=4.0.0; extra == 'dev'
Requires-Dist: pytest>=7.0.0; extra == 'dev'
Requires-Dist: ruff>=0.1.0; extra == 'dev'
Requires-Dist: types-pyyaml>=6.0.0; extra == 'dev'
Provides-Extra: docs
Requires-Dist: furo>=2024.8.6; extra == 'docs'
Requires-Dist: linkify-it-py>=2.0.3; extra == 'docs'
Requires-Dist: myst-parser>=4.0.1; extra == 'docs'
Requires-Dist: sphinx-design>=0.6.1; extra == 'docs'
Requires-Dist: sphinx>=8.2.3; extra == 'docs'
Requires-Dist: sphinxcontrib-mermaid>=1.0.0; extra == 'docs'
